openrazer_daemon/__init__.py
openrazer_daemon-0.0.1.dist-info/METADATA
openrazer_daemon-0.0.1.dist-info/WHEEL
openrazer_daemon-0.0.1.dist-info/top_level.txt
openrazer_daemon-0.0.1.dist-info/RECORD
