Metadata-Version: 2.1
Name: openrazer-daemon
Version: 0.0.1
Summary: OpenRazer userspace daemon that abstracts access to the kernel driver.
